{
    "joints": {
        "id": "OUT",
        "in": [
            0.520469,
            0.55066
        ],
        "out": [
            [
                0.517391,
                0.81667,
                "ANY"
            ],
            [
                0.780399,
                0.230463,
                "ANY"
            ],
            [
                0.299949,
                0.17135,
                "ANY"
            ]
        ],
        "texture": 2055
    },
    "textures": [
        {
            "component": "Pelvis",
            "id": 2055
        }
    ]
}