{
    "joints": {
        "components": [
            {
                "components": [
                    {
                        "id": "Nose",
                        "in": [
                            329.176897,
                            -677.88
                        ],
                        "out": [
                            [
                                329.176897,
                                -677.88,
                                "ANY"
                            ]
                        ],
                        "texture": 1522
                    },
                    {
                        "components": [
                            {
                                "id": "Left Pupil",
                                "in": [
                                    0.507609,
                                    0.473506
                                ],
                                "out": [
                                    [
                                        0.507609,
                                        0.473506,
                                        "ANY"
                                    ]
                                ],
                                "texture": 1527
                            }
                        ],
                        "id": "Left Eye",
                        "in": [
                            0.510229,
                            0.511567
                        ],
                        "out": [
                            [
                                0.510229,
                                0.511567,
                                "ANY"
                            ]
                        ],
                        "texture": 1524
                    },
                    {
                        "components": [
                            {
                                "id": "Right Pupil",
                                "in": [
                                    0.452329,
                                    0.473506
                                ],
                                "out": [
                                    [
                                        0.452329,
                                        0.473506,
                                        "ANY"
                                    ]
                                ],
                                "texture": 1528
                            }
                        ],
                        "id": "Right Eye",
                        "in": [
                            0.463107,
                            0.511567
                        ],
                        "out": [
                            [
                                0.463107,
                                0.511567,
                                "ANY"
                            ]
                        ],
                        "texture": 1523
                    },
                    {
                        "id": "Left Eyebrow",
                        "in": [
                            0.522973,
                            0.507848
                        ],
                        "out": [
                            [
                                0.522973,
                                0.507848,
                                "ANY"
                            ]
                        ],
                        "texture": 1526
                    },
                    {
                        "id": "Right Eyebrow",
                        "in": [
                            0.494858,
                            0.562098
                        ],
                        "out": [
                            [
                                0.494858,
                                0.562098,
                                "ANY"
                            ]
                        ],
                        "texture": 1525
                    }
                ],
                "id": "Upper Jaw",
                "in": [
                    0.573352,
                    0.580489
                ],
                "out": [
                    [
                        0.551283,
                        0.629818,
                        "ANY"
                    ],
                    [
                        0.394292,
                        0.674215,
                        "ANY"
                    ],
                    [
                        0.726221,
                        0.684081,
                        "ANY"
                    ],
                    [
                        0.4692,
                        0.749195,
                        "ANY"
                    ],
                    [
                        0.665075,
                        0.755114,
                        "ANY"
                    ]
                ],
                "texture": 1521
            }
        ],
        "id": "Lower Jaw",
        "in": [
            0.497133,
            0.179042
        ],
        "out": [
            [
                0.419589,
                1.0077,
                "ANY"
            ]
        ],
        "texture": 1520
    },
    "textures": [
        {
            "component": "Lower Jaw",
            "id": 1520
        },
        {
            "component": "Upper Jaw",
            "id": 1521
        },
        {
            "component": "Nose",
            "id": 1522
        },
        {
            "component": "Right Eye",
            "id": 1523
        },
        {
            "component": "Left Eye",
            "id": 1524
        },
        {
            "component": "Right Eyebrow",
            "id": 1525
        },
        {
            "component": "Left Eyebrow",
            "id": 1526
        },
        {
            "component": "Left Pupil",
            "id": 1527
        },
        {
            "component": "Right Pupil",
            "id": 1528
        }
    ]
}