{
    "joints": {
        "id": "OUT",
        "in": [
            0.501148,
            0.399018
        ],
        "out": [
            [
                0.493523,
                0.712655,
                "ANY"
            ],
            [
                0.78105,
                0.321745,
                "ANY"
            ],
            [
                0.200561,
                0.244473,
                "ANY"
            ]
        ],
        "texture": 264
    },
    "textures": [
        {
            "component": "Pelvis",
            "id": 264
        }
    ]
}