{
    "joints": {
        "components": [
            {
                "components": [
                    {
                        "id": "Hand",
                        "in": [
                            0.733005,
                            0.881445
                        ],
                        "out": [
                            [
                                0.572918,
                                0.125143,
                                "ANY"
                            ]
                        ],
                        "texture": 347
                    }
                ],
                "id": "Lower Arm",
                "in": [
                    0.655182,
                    0.987401
                ],
                "out": [
                    [
                        0.335431,
                        0.059865,
                        "ANY"
                    ]
                ],
                "texture": 346
            }
        ],
        "id": "Upper Arm",
        "in": [
            0.457617,
            0.888031
        ],
        "out": [
            [
                0.493179,
                0.122865,
                "ANY"
            ]
        ],
        "texture": 345
    },
    "textures": [
        {
            "component": "Upper Arm",
            "id": 345
        },
        {
            "component": "Lower Arm",
            "id": 346
        },
        {
            "component": "Hand",
            "id": 347
        }
    ]
}